odoo10_addon_delivery_auto_refresh-10.0.1.0.0-py2.7-nspkg.pth
odoo/addons/delivery_auto_refresh/README.rst
odoo/addons/delivery_auto_refresh/__init__.py
odoo/addons/delivery_auto_refresh/__manifest__.py
odoo/addons/delivery_auto_refresh/data/ir_config_parameter.xml
odoo/addons/delivery_auto_refresh/models/__init__.py
odoo/addons/delivery_auto_refresh/models/sale_order.py
odoo/addons/delivery_auto_refresh/models/stock_picking.py
odoo/addons/delivery_auto_refresh/tests/__init__.py
odoo/addons/delivery_auto_refresh/tests/test_delivery_auto_refresh.py
odoo10_addon_delivery_auto_refresh-10.0.1.0.0.dist-info/DESCRIPTION.rst
odoo10_addon_delivery_auto_refresh-10.0.1.0.0.dist-info/METADATA
odoo10_addon_delivery_auto_refresh-10.0.1.0.0.dist-info/RECORD
odoo10_addon_delivery_auto_refresh-10.0.1.0.0.dist-info/WHEEL
odoo10_addon_delivery_auto_refresh-10.0.1.0.0.dist-info/metadata.json
odoo10_addon_delivery_auto_refresh-10.0.1.0.0.dist-info/namespace_packages.txt
odoo10_addon_delivery_auto_refresh-10.0.1.0.0.dist-info/top_level.txt
